{
    "27UP850-W": {
        "valoracion": {
            "de cuanto": "3/5 estrellas (1 valoración)"
        },
        "fabricante": {
            "cual": "LG"
        },
        "web": {
            "cual": "https://www.lg.com/es/monitores/lg-27up850-w"
        },
        "pantalla": {
            "tamanio": {
                "de cuanto": "27 pulgadas"
            },
            "resolucion": {
                "de cuanto": "3840x2160 px"
            },
            "ratioAspecto": {
                "de cuanto": "16:9"
            },
            "tecnologiaRetroiluminacion": {
                "cual": "LED"
            },
            "brilloMin": {
                "de cuanto": "320 cd/m^2"
            },
            "brilloTip": {
                "de cuanto": "400 cd/m^2"
            },
            "ratioContrasteMin": {
                "de cuanto": "1000:1"
            },
            "ratioContrasteTip": {
                "de cuanto": "1200:1"
            },
            "velocidadRespuesta": {
                "de cuanto": "5 ms"
            },
            "profundidadColor": {
                "de cuanto": "1.07B"
            },
            "tipoPanel": {
                "cual": "IPS"
            },
            "curva": {
                "tiene": false
            },
            "anguloVisionR/L": {
                "de cuanto": "178"
            },
            "anguloVisionU/D": {
                "de cuanto": "178"
            }
        },
        "atributos": {
            "HDR": {
                "tiene": "10"
            },
            "FreeSync": {
                "tiene": true
            },
            "GSync": {
                "tiene": false
            },
            "overclock": {
                "tiene": false
            },
            "ahorroEnergia": {
                "tiene": true
            },
            "microfono": {
                "tiene": false
            },
            "webCam": {
                "tiene": false
            },
            "FPSCounter": {
                "tiene": false
            }
        },
        "conectividad": {
            "entradasHDMI": {
                "cuanto": "2"
            }
        }
    }
}